randomize_songs-1.0.0.dist-info/METADATA
randomize_songs-1.0.0.dist-info/WHEEL
randomize_songs-1.0.0.dist-info/entry_points.txt
randomize_songs/__about__.py
randomize_songs/__init__.py
randomize_songs/__main__.py
randomize_songs/cli.py
randomize_songs/core.py
randomize_songs/main.py
randomize_songs-1.0.0.dist-info/RECORD
