Metadata-Version: 2.1
Name: randomize-songs
Version: 1.0.0
Summary: Utility for randomizing songs
Keywords: song,music,mp3
Author-Email: Cujoko <cujoko@gmail.com>
Classifier: Development Status :: 5 - Production/Stable
Classifier: Intended Audience :: End Users/Desktop
Classifier: License :: OSI Approved :: MIT License
Classifier: Programming Language :: Python :: 3
Classifier: Topic :: Utilities
Project-URL: repository, https://github.com/Cujoko/randomize-songs
Requires-Python: >=3.10
